50-capablerobot-usbhub.rules
CODE_OF_CONDUCT.md
LICENSE
capablerobot_usbhub/__init__.py
capablerobot_usbhub/config.py
capablerobot_usbhub/console.py
capablerobot_usbhub/device.py
capablerobot_usbhub/formats/usb4715.ksy
capablerobot_usbhub/formats/usb4715_gpio.ksy
capablerobot_usbhub/formats/usb4715_main.ksy
capablerobot_usbhub/formats/usb4715_mcu.ksy
capablerobot_usbhub/formats/usb4715_port.ksy
capablerobot_usbhub/gpio.py
capablerobot_usbhub/i2c.py
capablerobot_usbhub/main.py
capablerobot_usbhub/power.py
capablerobot_usbhub/registers/__init__.py
capablerobot_usbhub/registers/gpio.py
capablerobot_usbhub/registers/main.py
capablerobot_usbhub/registers/port.py
capablerobot_usbhub/spi.py
capablerobot_usbhub/util.py
capablerobot_usbhub/windows/32bit/libusb-1.0.dll
capablerobot_usbhub/windows/32bit/libusb-1.0.lib
capablerobot_usbhub/windows/32bit/libusb-1.0.pdb
capablerobot_usbhub/windows/64bit/libusb-1.0.dll
capablerobot_usbhub/windows/64bit/libusb-1.0.lib
capablerobot_usbhub/windows/64bit/libusb-1.0.pdb
capablerobot_usbhub/windows/README.md
requirements.txt
capablerobot_usbhub-0.5.0.dist-info/entry_points.txt
capablerobot_usbhub-0.5.0.dist-info/LICENSE
capablerobot_usbhub-0.5.0.dist-info/WHEEL
capablerobot_usbhub-0.5.0.dist-info/METADATA
capablerobot_usbhub-0.5.0.dist-info/RECORD
