Metadata-Version: 2.1
Name: capablerobot-usbhub
Version: 0.5.0
Summary: Host side driver for the Capable Robot Programmable USB Hub
Home-page: https://github.com/CapableRobot/CapableRobot_USBHub_Driver
License: MIT
Keywords: usb,circuitpython,hardware
Author: Chris Osterwood
Author-email: osterwood@capablerobot.com
Requires-Python: >=3.6,<4.0
Classifier: License :: OSI Approved :: MIT License
Classifier: Programming Language :: Python :: 3
Classifier: Programming Language :: Python :: 3.6
Classifier: Programming Language :: Python :: 3.7
Classifier: Programming Language :: Python :: 3.8
Classifier: Programming Language :: Python :: 3.9
Requires-Dist: click (>=7.0,<8.0)
Requires-Dist: construct (>=2.9.51,<3.0.0)
Requires-Dist: pyusb (>=1.0.2,<2.0.0)
Requires-Dist: pyyaml (>=5.3,<6.0)
Project-URL: Repository, https://github.com/CapableRobot/CapableRobot_USBHub_Driver
